homepage/__init__.py
homepage/__main__.py
homepage/homepage.py
homepage/install_packages.py
homepage/static/HomePage.png
homepage/static/bg.webp
homepage/static/favicon.png
homepage/static/script.js
homepage/static/script.min.js
homepage/static/styles.css
homepage/static/styles.min.css
homepage/templates/error_template.html
homepage/templates/site.html
homepage-0.5.7.dist-info/entry_points.txt
homepage-0.5.7.dist-info/LICENSE
homepage-0.5.7.dist-info/WHEEL
homepage-0.5.7.dist-info/METADATA
homepage-0.5.7.dist-info/RECORD
