Metadata-Version: 2.1
Name: homepage
Version: 0.5.7
Summary: A simple flask webapp to download the audio track from almost any internet video.
Home-page: https://github.com/Sh3llcod3/HomePage
License: MIT
Author: Sh3llcod3
Author-email: 28938427+Sh3llcod3@users.noreply.github.com
Requires-Python: >=3.6,<4.0
Classifier: Environment :: Web Environment
Classifier: Framework :: Flask
Classifier: License :: OSI Approved :: MIT License
Classifier: Programming Language :: Python :: 3
Classifier: Programming Language :: Python :: 3.10
Classifier: Programming Language :: Python :: 3.6
Classifier: Programming Language :: Python :: 3.7
Classifier: Programming Language :: Python :: 3.8
Classifier: Programming Language :: Python :: 3.9
Classifier: Topic :: Multimedia :: Sound/Audio
Requires-Dist: Flask
Requires-Dist: easyparse
Requires-Dist: gevent
Requires-Dist: yt-dlp
Project-URL: Repository, https://github.com/Sh3llcod3/HomePage
